markdown_manuscript_filters/__init__.py
markdown_manuscript_filters/compile_markdown.py
markdown_manuscript_filters/compile_markdown_imports.py
markdown_manuscript_filters/latex_to_speech.py
markdown_manuscript_filters/markdown_to_mp3.py
markdown_manuscript_filters/pyrex.py
markdown_manuscript_filters/unicode_to_latex.py
markdown_manuscript_filters/yaml_funs.py
markdown_manuscript_filters-0.1.7.dist-info/LICENSE
markdown_manuscript_filters-0.1.7.dist-info/METADATA
markdown_manuscript_filters-0.1.7.dist-info/WHEEL
markdown_manuscript_filters-0.1.7.dist-info/top_level.txt
markdown_manuscript_filters-0.1.7.dist-info/RECORD
