Metadata-Version: 2.1
Name: markdown-manuscript-filters
Version: 0.1.7
Summary: python scripts and panflute filters for producing technical documents from markdown
Home-page: https://github.com/awillats/markdown-manuscript-filters
Author: Adam Willats
Author-email: adamwillats@gmail.com
License: UNKNOWN
Project-URL: Bug Tracker, https://github.com/awillats/markdown_manuscript_filters/issues
Platform: UNKNOWN
Classifier: Programming Language :: Python :: 3
Classifier: License :: OSI Approved :: GNU General Public License v3 (GPLv3)
Classifier: Operating System :: OS Independent
Requires-Python: >=3.6
License-File: LICENSE
